{
  "annotations": {
    "list": [
      {
        "builtIn": 1,
        "datasource": {
          "type": "grafana",
          "uid": "-- Grafana --"
        },
        "enable": true,
        "hide": true,
        "iconColor": "rgba(0, 211, 255, 1)",
        "name": "Annotations & Alerts",
        "type": "dashboard"
      }
    ]
  },
  "editable": true,
  "fiscalYearStartMonth": 0,
  "graphTooltip": 0,
  "id": 1,
  "links": [],
  "liveNow": true,
  "panels": [
    {
      "collapsed": false,
      "gridPos": {
        "h": 1,
        "w": 24,
        "x": 0,
        "y": 0
      },
      "id": 8,
      "panels": [],
      "title": "Observations",
      "type": "row"
    },
    {
      "datasource": {
        "type": "influxdb",
        "uid": "ef3qf33lahx4wa"
      },
      "fieldConfig": {
        "defaults": {
          "color": {
            "mode": "palette-classic"
          },
          "custom": {
            "axisBorderShow": false,
            "axisCenteredZero": false,
            "axisColorMode": "text",
            "axisLabel": "",
            "axisPlacement": "auto",
            "barAlignment": 0,
            "drawStyle": "line",
            "fillOpacity": 0,
            "gradientMode": "none",
            "hideFrom": {
              "legend": false,
              "tooltip": false,
              "viz": false
            },
            "insertNulls": false,
            "lineInterpolation": "linear",
            "lineWidth": 1,
            "pointSize": 5,
            "scaleDistribution": {
              "type": "linear"
            },
            "showPoints": "auto",
            "spanNulls": false,
            "stacking": {
              "group": "A",
              "mode": "none"
            },
            "thresholdsStyle": {
              "mode": "off"
            }
          },
          "mappings": [],
          "thresholds": {
            "mode": "absolute",
            "steps": [
              {
                "color": "green",
                "value": null
              },
              {
                "color": "red",
                "value": 80
              }
            ]
          }
        },
        "overrides": []
      },
      "gridPos": {
        "h": 12,
        "w": 18,
        "x": 0,
        "y": 1
      },
      "id": 1,
      "options": {
        "legend": {
          "calcs": [],
          "displayMode": "list",
          "placement": "bottom",
          "showLegend": true
        },
        "tooltip": {
          "mode": "single",
          "sort": "none"
        }
      },
      "targets": [
        {
          "datasource": {
            "type": "influxdb",
            "uid": "ef3qf33lahx4wa"
          },
          "query": "SELECT mean(\"avg_amount\") FROM \"avg_amount_by_category\" WHERE $timeFilter GROUP BY time(1m), \"merchant_category\" fill(null)",
          "rawQuery": true,
          "refId": "A",
          "resultFormat": "time_series"
        }
      ],
      "title": "Average Transaction Amount by Category",
      "type": "timeseries"
    },
    {
      "datasource": {},
      "fieldConfig": {
        "defaults": {
          "color": {
            "mode": "palette-classic"
          },
          "custom": {
            "axisBorderShow": false,
            "axisCenteredZero": false,
            "axisColorMode": "text",
            "axisLabel": "",
            "axisPlacement": "auto",
            "barAlignment": 0,
            "drawStyle": "line",
            "fillOpacity": 0,
            "gradientMode": "none",
            "hideFrom": {
              "legend": false,
              "tooltip": false,
              "viz": false
            },
            "insertNulls": false,
            "lineInterpolation": "linear",
            "lineWidth": 1,
            "pointSize": 5,
            "scaleDistribution": {
              "type": "linear"
            },
            "showPoints": "auto",
            "spanNulls": false,
            "stacking": {
              "group": "A",
              "mode": "none"
            },
            "thresholdsStyle": {
              "mode": "off"
            }
          },
          "mappings": [],
          "thresholds": {
            "mode": "absolute",
            "steps": [
              {
                "color": "green",
                "value": null
              },
              {
                "color": "red",
                "value": 80
              }
            ]
          }
        },
        "overrides": []
      },
      "gridPos": {
        "h": 9,
        "w": 18,
        "x": 0,
        "y": 13
      },
      "id": 2,
      "options": {
        "legend": {
          "calcs": [],
          "displayMode": "list",
          "placement": "bottom",
          "showLegend": true
        },
        "tooltip": {
          "mode": "single",
          "sort": "none"
        }
      },
      "targets": [
        {
          "datasource": {
            "type": "influxdb",
            "uid": "ef3qf33lahx4wa"
          },
          "query": "SELECT sum(\"txn_count\") FROM \"txn_count_by_region\" WHERE $timeFilter GROUP BY time(1m), \"region\" fill(null)",
          "rawQuery": true,
          "refId": "B",
          "resultFormat": "time_series"
        }
      ],
      "title": "Transaction Count by Region",
      "type": "timeseries"
    },
    {
      "datasource": {
        "type": "influxdb",
        "uid": "ef3qf33lahx4wa"
      },
      "fieldConfig": {
        "defaults": {
          "custom": {
            "align": "left",
            "cellOptions": {
              "type": "auto"
            },
            "inspect": false
          },
          "mappings": [],
          "thresholds": {
            "mode": "absolute",
            "steps": [
              {
                "color": "green",
                "value": null
              },
              {
                "color": "red",
                "value": 80
              }
            ]
          }
        },
        "overrides": []
      },
      "gridPos": {
        "h": 8,
        "w": 24,
        "x": 0,
        "y": 22
      },
      "id": 9,
      "options": {
        "cellHeight": "sm",
        "fontSize": "100%",
        "footer": {
          "countRows": false,
          "fields": "",
          "reducer": [
            "sum"
          ],
          "show": false
        },
        "showHeader": true,
        "sortBy": []
      },
      "pluginVersion": "10.4.3",
      "targets": [
        {
          "datasource": {
            "type": "influxdb",
            "uid": "ef3qf33lahx4wa"
          },
          "query": "SELECT \"transaction_id\", \"client_id\", \"amount\", \"location\", \"region\", \"merchant_category\", \"device\"\nFROM \"raw_transactions\"\nWHERE $timeFilter\nORDER BY time DESC\nLIMIT 20",
          "rawQuery": true,
          "refId": "C",
          "resultFormat": "table"
        }
      ],
      "title": "Latest Transactions Sample",
      "type": "table"
    },
    {
      "datasource": {
        "type": "influxdb",
        "uid": "ef3qf33lahx4wa"
      },
      "fieldConfig": {
        "defaults": {
          "color": {
            "mode": "thresholds"
          },
          "custom": {
            "align": "left",
            "cellOptions": {
              "type": "auto"
            },
            "inspect": false
          },
          "mappings": [],
          "thresholds": {
            "mode": "absolute",
            "steps": [
              {
                "color": "green",
                "value": null
              },
              {
                "color": "red",
                "value": 80
              }
            ]
          }
        },
        "overrides": []
      },
      "gridPos": {
        "h": 8,
        "w": 24,
        "x": 0,
        "y": 30
      },
      "id": 10,
      "options": {
        "cellHeight": "sm",
        "fontSize": "100%",
        "footer": {
          "countRows": false,
          "fields": "",
          "reducer": [
            "sum"
          ],
          "show": false
        },
        "showHeader": true,
        "sortBy": []
      },
      "pluginVersion": "10.4.3",
      "targets": [
        {
          "datasource": {
            "type": "influxdb",
            "uid": "ef3qf33lahx4wa"
          },
          "query": "SELECT \"client_id\", \"region_count\", \"regions_seen_str\"\nFROM \"impossible_travel_alerts\"\nWHERE $timeFilter  ",
          "rawQuery": true,
          "refId": "C",
          "resultFormat": "table"
        }
      ],
      "title": "Impossible Travel Fraud",
      "type": "table"
    },
    {
      "datasource": {
        "type": "influxdb",
        "uid": "ef3qf33lahx4wa"
      },
      "fieldConfig": {
        "defaults": {
          "color": {
            "mode": "thresholds"
          },
          "custom": {
            "align": "auto",
            "cellOptions": {
              "type": "auto"
            },
            "inspect": false
          },
          "mappings": [],
          "thresholds": {
            "mode": "absolute",
            "steps": [
              {
                "color": "green",
                "value": null
              },
              {
                "color": "red",
                "value": 80
              }
            ]
          }
        },
        "overrides": []
      },
      "gridPos": {
        "h": 8,
        "w": 24,
        "x": 0,
        "y": 38
      },
      "id": 11,
      "options": {
        "cellHeight": "sm",
        "fontSize": "100%",
        "footer": {
          "countRows": false,
          "fields": "",
          "reducer": [
            "sum"
          ],
          "show": false
        },
        "showHeader": true,
        "sortBy": []
      },
      "pluginVersion": "10.4.3",
      "targets": [
        {
          "datasource": {
            "type": "influxdb",
            "uid": "ef3qf33lahx4wa"
          },
          "query": "SELECT \"client_id\", \"categories_seen_str\", \"category_count\"\nFROM \"spending_spree_alerts\"\nWHERE $timeFilter",
          "rawQuery": true,
          "refId": "C",
          "resultFormat": "table"
        }
      ],
      "title": "Suspicious Spending Spree Fraud",
      "type": "table"
    },
    {
      "datasource": {
        "type": "influxdb",
        "uid": "ef3qf33lahx4wa"
      },
      "fieldConfig": {
        "defaults": {
          "color": {
            "mode": "thresholds"
          },
          "custom": {
            "align": "auto",
            "cellOptions": {
              "type": "auto"
            },
            "inspect": false
          },
          "mappings": [],
          "thresholds": {
            "mode": "absolute",
            "steps": [
              {
                "color": "green",
                "value": null
              },
              {
                "color": "red",
                "value": 80
              }
            ]
          }
        },
        "overrides": []
      },
      "gridPos": {
        "h": 8,
        "w": 24,
        "x": 0,
        "y": 46
      },
      "id": 12,
      "options": {
        "cellHeight": "sm",
        "fontSize": "100%",
        "footer": {
          "countRows": false,
          "fields": "",
          "reducer": [
            "sum"
          ],
          "show": false
        },
        "showHeader": true,
        "sortBy": []
      },
      "pluginVersion": "10.4.3",
      "targets": [
        {
          "datasource": {
            "type": "influxdb",
            "uid": "ef3qf33lahx4wa"
          },
          "query": "SELECT \"client_id\", \"min_amount\", \"max_amount\"\nFROM \"low_high_velocity_alerts\"\nWHERE $timeFilter",
          "rawQuery": true,
          "refId": "C",
          "resultFormat": "table"
        }
      ],
      "title": "High velocity Fraud",
      "type": "table"
    },
    {
      "collapsed": false,
      "gridPos": {
        "h": 1,
        "w": 24,
        "x": 0,
        "y": 54
      },
      "id": 6,
      "panels": [],
      "title": "Client observations",
      "type": "row"
    },
    {
      "datasource": {
        "type": "influxdb",
        "uid": "ef3qf33lahx4wa"
      },
      "fieldConfig": {
        "defaults": {
          "color": {
            "mode": "palette-classic"
          },
          "custom": {
            "axisBorderShow": false,
            "axisCenteredZero": false,
            "axisColorMode": "text",
            "axisLabel": "",
            "axisPlacement": "auto",
            "barAlignment": 0,
            "drawStyle": "line",
            "fillOpacity": 0,
            "gradientMode": "none",
            "hideFrom": {
              "legend": false,
              "tooltip": false,
              "viz": false
            },
            "insertNulls": false,
            "lineInterpolation": "linear",
            "lineWidth": 1,
            "pointSize": 5,
            "scaleDistribution": {
              "type": "linear"
            },
            "showPoints": "auto",
            "spanNulls": false,
            "stacking": {
              "group": "A",
              "mode": "none"
            },
            "thresholdsStyle": {
              "mode": "off"
            }
          },
          "mappings": [],
          "thresholds": {
            "mode": "absolute",
            "steps": [
              {
                "color": "green",
                "value": null
              },
              {
                "color": "red",
                "value": 80
              }
            ]
          }
        },
        "overrides": []
      },
      "gridPos": {
        "h": 8,
        "w": 12,
        "x": 0,
        "y": 55
      },
      "id": 5,
      "options": {
        "legend": {
          "calcs": [],
          "displayMode": "list",
          "placement": "bottom",
          "showLegend": true
        },
        "tooltip": {
          "mode": "single",
          "sort": "none"
        }
      },
      "targets": [
        {
          "datasource": {
            "type": "influxdb",
            "uid": "ef3qf33lahx4wa"
          },
          "query": "SELECT CUMULATIVE_SUM(sum(\"amount\"))\nFROM \"raw_transactions\"\nWHERE \"client_id\" =~ /$client_id$/ AND $timeFilter\nGROUP BY time($__interval), \"client_id\"",
          "rawQuery": true,
          "refId": "A",
          "resultFormat": "time_series"
        }
      ],
      "title": "Sum of the amounts per client",
      "type": "timeseries"
    }
  ],
  "refresh": "5s",
  "schemaVersion": 39,
  "tags": [
    "real-time",
    "transactions"
  ],
  "templating": {
    "list": [
      {
        "current": {
          "selected": true,
          "text": "10",
          "value": "10"
        },
        "definition": "SHOW TAG VALUES FROM \"raw_transactions\" WITH KEY = \"client_id\"",
        "hide": 0,
        "includeAll": true,
        "multi": false,
        "name": "client_id",
        "options": [],
        "query": "SHOW TAG VALUES FROM \"raw_transactions\" WITH KEY = \"client_id\"",
        "refresh": 1,
        "regex": "",
        "skipUrlSync": false,
        "sort": 0,
        "type": "query"
      }
    ]
  },
  "time": {
    "from": "now-15m",
    "to": "now"
  },
  "timepicker": {},
  "timezone": "browser",
  "title": "Real-Time Customer Behavior",
  "uid": "customer_behavior_dashboard",
  "version": 1,
  "weekStart": ""
}